code_tokenizer/__init__.py
code_tokenizer/__main__.py
code_tokenizer/code_collector.py
code_tokenizer/constants.py
code_tokenizer/core.py
code_tokenizer/main.py
code_tokenizer/table_width_manager.py
code_tokenizer/utils.py
code_tokenizer-1.0.3.dist-info/METADATA
code_tokenizer-1.0.3.dist-info/WHEEL
code_tokenizer-1.0.3.dist-info/entry_points.txt
code_tokenizer-1.0.3.dist-info/licenses/LICENSE
code_tokenizer-1.0.3.dist-info/RECORD
