Metadata-Version: 2.4
Name: code-tokenizer
Version: 1.0.3
Summary: A professional CLI tool for counting AI model tokens in code projects
Project-URL: Documentation, https://github.com/org-hex/code-tokenizer#readme
Project-URL: Homepage, https://github.com/org-hex/code-tokenizer
Project-URL: Repository, https://github.com/org-hex/code-tokenizer.git
Project-URL: Issues, https://github.com/org-hex/code-tokenizer/issues
Author: Code Tokenizer Contributors
Maintainer: Code Tokenizer Contributors
License-Expression: MIT
License-File: LICENSE
Keywords: ai,claude,cli,code-analysis,gpt,llm,openai,tokens
Classifier: Development Status :: 5 - Production/Stable
Classifier: Intended Audience :: Developers
Classifier: License :: OSI Approved :: MIT License
Classifier: Operating System :: OS Independent
Classifier: Programming Language :: Python :: 3
Classifier: Programming Language :: Python :: 3.10
Classifier: Programming Language :: Python :: 3.11
Classifier: Programming Language :: Python :: 3.12
Classifier: Programming Language :: Python :: 3.13
Classifier: Topic :: Software Development :: Libraries :: Python Modules
Classifier: Topic :: Text Processing
Classifier: Topic :: Utilities
Requires-Python: >=3.10
Requires-Dist: click>=8.3.0
Requires-Dist: rich>=14.2.0
Requires-Dist: tiktoken>=0.12.0
Provides-Extra: dev
Requires-Dist: black>=24.0.0; extra == 'dev'
Requires-Dist: flake8>=7.0.0; extra == 'dev'
Requires-Dist: isort>=5.13.0; extra == 'dev'
Requires-Dist: mypy>=1.8.0; extra == 'dev'
Requires-Dist: pytest-cov>=4.0.0; extra == 'dev'
Requires-Dist: pytest>=8.0.0; extra == 'dev'
Requires-Dist: safety>=3.0.0; extra == 'dev'
